madeira_utils/__init__.py
madeira_utils/api_common.py
madeira_utils/api_dev.py
madeira_utils/aws_lambda_responses.py
madeira_utils/dns.py
madeira_utils/godaddy_dns.py
madeira_utils/hashing.py
madeira_utils/loggers.py
madeira_utils/measurement.py
madeira_utils/time.py
madeira_utils/utils.py
madeira_utils-1.0.15.dist-info/METADATA
madeira_utils-1.0.15.dist-info/WHEEL
madeira_utils-1.0.15.dist-info/top_level.txt
madeira_utils-1.0.15.dist-info/RECORD
