Metadata-Version: 2.1
Name: madeira-utils
Version: 1.0.15
Summary: Madeira Utilities
Home-page: https://github.com/mxmader/madeira-utils
Author: Joe Mader
Author-email: jmader@jmader.com
License: MIT
Platform: UNKNOWN
Classifier: License :: OSI Approved :: MIT License
Classifier: Programming Language :: Python :: 3
Classifier: Programming Language :: Python :: 3.8
Classifier: Programming Language :: Python :: 3.9
Requires-Dist: dnspython
Requires-Dist: falcon (==3.0.1)
Requires-Dist: pyyaml
Requires-Dist: requests
